aats/__init__.py
aats/base_strategy.py
aats/control_service.py
aats/market_service.py
aats/trade_service.py
aats/base/__init__.py
aats/base/const.py
aats/base/manager.py
aats/base/order.py
aats/base/singleton.py
aats/base/symbolinfo.py
aats/base/utils.py
aats-0.1.2.dist-info/METADATA
aats-0.1.2.dist-info/WHEEL
aats-0.1.2.dist-info/licenses/LICENSE
aats-0.1.2.dist-info/RECORD
